<stg><name>MatMul_QK_tiled<17, 48, 17, 1, 1, 1, 1, 1, 137, 16, 0, ap_int<8>, ap_int<32> >.20</name>


<trans_list>

<trans id="37" from="1" to="2">
<condition id="-1">
<or_exp><and_exp></and_exp></or_exp>
</condition>
</trans>

<trans id="38" from="2" to="3">
<condition id="-1">
<or_exp><and_exp></and_exp></or_exp>
</condition>
</trans>

<trans id="39" from="3" to="4">
<condition id="-1">
<or_exp><and_exp></and_exp></or_exp>
</condition>
</trans>

<trans id="40" from="4" to="5">
<condition id="-1">
<or_exp><and_exp><literal name="icmp_ln1678" val="0"/>
</and_exp></or_exp>
</condition>
</trans>

<trans id="42" from="5" to="6">
<condition id="-1">
<or_exp><and_exp></and_exp></or_exp>
</condition>
</trans>

<trans id="43" from="6" to="7">
<condition id="-1">
<or_exp><and_exp></and_exp></or_exp>
</condition>
</trans>

<trans id="44" from="7" to="8">
<condition id="-1">
<or_exp><and_exp></and_exp></or_exp>
</condition>
</trans>

<trans id="45" from="8" to="4">
<condition id="-1">
<or_exp><and_exp></and_exp></or_exp>
</condition>
</trans>
</trans_list>



<state_list>

<state id="1" st_id="1">

<operation id="9" st_id="1" stage="1" lat="1">
<core>NULL</core>
<MemPortIdVec></MemPortIdVec>
<condition id="-1">
<or_exp><and_exp></and_exp></or_exp>
</condition>

<Node id="4" bw="5" op_0_bw="32">
<![CDATA[
entry:0 %m = alloca i32 1

]]></Node>
<StgValue><ssdm name="m"/></StgValue>
</operation>

<operation id="10" st_id="1" stage="1" lat="1">
<core>NULL</core>
<MemPortIdVec></MemPortIdVec>
<condition id="-1">
<or_exp><and_exp></and_exp></or_exp>
</condition>

<Node id="8" bw="8" op_0_bw="64">
<![CDATA[
entry:4 %buff_K_V = alloca i64 1

]]></Node>
<StgValue><ssdm name="buff_K_V"/><MemPortTyVec>2 1 1 1 1 1 1 1 1 1 1 1 1 1 1 1 3 </MemPortTyVec>
</StgValue>
</operation>

<operation id="11" st_id="1" stage="1" lat="1">
<core>NULL</core>
<MemPortIdVec></MemPortIdVec>
<condition id="-1">
<or_exp><and_exp></and_exp></or_exp>
</condition>

<Node id="9" bw="8" op_0_bw="64">
<![CDATA[
entry:5 %tile_Q_V_0 = alloca i64 1

]]></Node>
<StgValue><ssdm name="tile_Q_V_0"/><MemPortTyVec>2 1 1 1 1 1 1 1 1 1 1 1 1 1 1 1 3 </MemPortTyVec>
</StgValue>
</operation>

<operation id="12" st_id="1" stage="1" lat="1">
<core>NULL</core>
<MemPortIdVec></MemPortIdVec>
<condition id="-1">
<or_exp><and_exp></and_exp></or_exp>
</condition>

<Node id="10" bw="32" op_0_bw="32">
<![CDATA[
entry:6 %empty = wait i32 @_ssdm_op_Wait

]]></Node>
<StgValue><ssdm name="empty"/></StgValue>
</operation>

<operation id="13" st_id="1" stage="2" lat="2">
<core></core>
<MemPortIdVec></MemPortIdVec>
<condition id="-1">
<or_exp><and_exp></and_exp></or_exp>
</condition>

<Node id="11" bw="0" op_0_bw="0" op_1_bw="8" op_2_bw="8" op_3_bw="0">
<![CDATA[
entry:7 %call_ln0 = call void @MatMul_QK_tiled.20_Pipeline_VITIS_LOOP_1656_1_VITIS_LOOP_1657_2, i8 %buff_K_V, i8 %K_1_2

]]></Node>
<StgValue><ssdm name="call_ln0"/></StgValue>
</operation>

<operation id="14" st_id="1" stage="1" lat="1">
<core>NULL</core>
<MemPortIdVec></MemPortIdVec>
<condition id="-1">
<or_exp><and_exp></and_exp></or_exp>
</condition>

<Node id="13" bw="0" op_0_bw="5" op_1_bw="5">
<![CDATA[
entry:9 %store_ln1678 = store i5 0, i5 %m

]]></Node>
<StgValue><ssdm name="store_ln1678"/></StgValue>
</operation>
</state>

<state id="2" st_id="2">

<operation id="15" st_id="2" stage="1" lat="2">
<core></core>
<MemPortIdVec></MemPortIdVec>
<condition id="-1">
<or_exp><and_exp></and_exp></or_exp>
</condition>

<Node id="11" bw="0" op_0_bw="0" op_1_bw="8" op_2_bw="8" op_3_bw="0">
<![CDATA[
entry:7 %call_ln0 = call void @MatMul_QK_tiled.20_Pipeline_VITIS_LOOP_1656_1_VITIS_LOOP_1657_2, i8 %buff_K_V, i8 %K_1_2

]]></Node>
<StgValue><ssdm name="call_ln0"/></StgValue>
</operation>
</state>

<state id="3" st_id="3">

<operation id="16" st_id="3" stage="1" lat="1">
<core>NULL</core>
<MemPortIdVec></MemPortIdVec>
<condition id="-1">
<or_exp><and_exp></and_exp></or_exp>
</condition>

<Node id="5" bw="0" op_0_bw="0" op_1_bw="8" op_2_bw="0" op_3_bw="32" op_4_bw="32" op_5_bw="0" op_6_bw="32" op_7_bw="32" op_8_bw="0" op_9_bw="0" op_10_bw="0" op_11_bw="32" op_12_bw="32" op_13_bw="32" op_14_bw="32" op_15_bw="0" op_16_bw="0" op_17_bw="32" op_18_bw="32">
<![CDATA[
entry:1 %specinterface_ln0 = specinterface void @_ssdm_op_SpecInterface, i8 %Q_1_2, void @empty_0, i32 0, i32 0, void @empty_26, i32 0, i32 0, void @empty_26, void @empty_26, void @empty_26, i32 0, i32 0, i32 0, i32 0, void @empty_26, void @empty_26, i32 4294967295, i32 0

]]></Node>
<StgValue><ssdm name="specinterface_ln0"/></StgValue>
</operation>

<operation id="17" st_id="3" stage="1" lat="1">
<core>NULL</core>
<MemPortIdVec></MemPortIdVec>
<condition id="-1">
<or_exp><and_exp></and_exp></or_exp>
</condition>

<Node id="6" bw="0" op_0_bw="0" op_1_bw="8" op_2_bw="0" op_3_bw="32" op_4_bw="32" op_5_bw="0" op_6_bw="32" op_7_bw="32" op_8_bw="0" op_9_bw="0" op_10_bw="0" op_11_bw="32" op_12_bw="32" op_13_bw="32" op_14_bw="32" op_15_bw="0" op_16_bw="0" op_17_bw="32" op_18_bw="32">
<![CDATA[
entry:2 %specinterface_ln0 = specinterface void @_ssdm_op_SpecInterface, i8 %K_1_2, void @empty_0, i32 0, i32 0, void @empty_26, i32 0, i32 0, void @empty_26, void @empty_26, void @empty_26, i32 0, i32 0, i32 0, i32 0, void @empty_26, void @empty_26, i32 4294967295, i32 0

]]></Node>
<StgValue><ssdm name="specinterface_ln0"/></StgValue>
</operation>

<operation id="18" st_id="3" stage="1" lat="1">
<core>NULL</core>
<MemPortIdVec></MemPortIdVec>
<condition id="-1">
<or_exp><and_exp></and_exp></or_exp>
</condition>

<Node id="7" bw="0" op_0_bw="0" op_1_bw="8" op_2_bw="0" op_3_bw="32" op_4_bw="32" op_5_bw="0" op_6_bw="32" op_7_bw="32" op_8_bw="0" op_9_bw="0" op_10_bw="0" op_11_bw="32" op_12_bw="32" op_13_bw="32" op_14_bw="32" op_15_bw="0" op_16_bw="0" op_17_bw="32" op_18_bw="32">
<![CDATA[
entry:3 %specinterface_ln0 = specinterface void @_ssdm_op_SpecInterface, i8 %A_2, void @empty_0, i32 0, i32 0, void @empty_26, i32 0, i32 0, void @empty_26, void @empty_26, void @empty_26, i32 0, i32 0, i32 0, i32 0, void @empty_26, void @empty_26, i32 4294967295, i32 0

]]></Node>
<StgValue><ssdm name="specinterface_ln0"/></StgValue>
</operation>

<operation id="19" st_id="3" stage="1" lat="1">
<core>NULL</core>
<MemPortIdVec></MemPortIdVec>
<condition id="-1">
<or_exp><and_exp></and_exp></or_exp>
</condition>

<Node id="12" bw="32" op_0_bw="32" op_1_bw="0" op_2_bw="0">
<![CDATA[
entry:8 %empty_292 = wait i32 @_ssdm_op_Wait

]]></Node>
<StgValue><ssdm name="empty_292"/></StgValue>
</operation>

<operation id="20" st_id="3" stage="1" lat="1">
<core>NULL</core>
<MemPortIdVec></MemPortIdVec>
<condition id="-1">
<or_exp><and_exp></and_exp></or_exp>
</condition>

<Node id="14" bw="0" op_0_bw="0">
<![CDATA[
entry:10 %br_ln1678 = br void %VITIS_LOOP_1681_5

]]></Node>
<StgValue><ssdm name="br_ln1678"/></StgValue>
</operation>
</state>

<state id="4" st_id="4">

<operation id="21" st_id="4" stage="1" lat="1">
<core>NULL</core>
<MemPortIdVec></MemPortIdVec>
<condition id="-1">
<or_exp><and_exp></and_exp></or_exp>
</condition>

<Node id="16" bw="5" op_0_bw="5" op_1_bw="0">
<![CDATA[
VITIS_LOOP_1681_5:0 %m_14 = load i5 %m

]]></Node>
<StgValue><ssdm name="m_14"/></StgValue>
</operation>

<operation id="22" st_id="4" stage="1" lat="1">
<core>Cmp</core>
<MemPortIdVec></MemPortIdVec>
<condition id="-1">
<or_exp><and_exp></and_exp></or_exp>
</condition>

<Node id="17" bw="1" op_0_bw="5" op_1_bw="5">
<![CDATA[
VITIS_LOOP_1681_5:1 %icmp_ln1678 = icmp_eq  i5 %m_14, i5 17

]]></Node>
<StgValue><ssdm name="icmp_ln1678"/></StgValue>
</operation>

<operation id="23" st_id="4" stage="1" lat="1">
<core>NULL</core>
<MemPortIdVec></MemPortIdVec>
<condition id="-1">
<or_exp><and_exp></and_exp></or_exp>
</condition>

<Node id="18" bw="32" op_0_bw="32" op_1_bw="64" op_2_bw="64" op_3_bw="64">
<![CDATA[
VITIS_LOOP_1681_5:2 %empty_293 = speclooptripcount i32 @_ssdm_op_SpecLoopTripCount, i64 17, i64 17, i64 17

]]></Node>
<StgValue><ssdm name="empty_293"/></StgValue>
</operation>

<operation id="24" st_id="4" stage="1" lat="1">
<core>Adder</core>
<MemPortIdVec></MemPortIdVec>
<condition id="-1">
<or_exp><and_exp></and_exp></or_exp>
</condition>

<Node id="19" bw="5" op_0_bw="5" op_1_bw="5">
<![CDATA[
VITIS_LOOP_1681_5:3 %m_15 = add i5 %m_14, i5 1

]]></Node>
<StgValue><ssdm name="m_15"/></StgValue>
</operation>

<operation id="25" st_id="4" stage="1" lat="1">
<core>NULL</core>
<MemPortIdVec></MemPortIdVec>
<condition id="-1">
<or_exp><and_exp></and_exp></or_exp>
</condition>

<Node id="20" bw="0" op_0_bw="1" op_1_bw="0" op_2_bw="0">
<![CDATA[
VITIS_LOOP_1681_5:4 %br_ln1678 = br i1 %icmp_ln1678, void %VITIS_LOOP_1681_5.split, void %for.end218

]]></Node>
<StgValue><ssdm name="br_ln1678"/></StgValue>
</operation>

<operation id="26" st_id="4" stage="1" lat="1">
<core>NULL</core>
<MemPortIdVec></MemPortIdVec>
<condition id="-1">
<or_exp><and_exp><literal name="icmp_ln1678" val="0"/>
</and_exp></or_exp>
</condition>

<Node id="23" bw="32" op_0_bw="32" op_1_bw="0">
<![CDATA[
VITIS_LOOP_1681_5.split:1 %empty_294 = wait i32 @_ssdm_op_Wait

]]></Node>
<StgValue><ssdm name="empty_294"/></StgValue>
</operation>

<operation id="27" st_id="4" stage="2" lat="2">
<core></core>
<MemPortIdVec></MemPortIdVec>
<condition id="-1">
<or_exp><and_exp><literal name="icmp_ln1678" val="0"/>
</and_exp></or_exp>
</condition>

<Node id="24" bw="0" op_0_bw="0" op_1_bw="8" op_2_bw="8" op_3_bw="0">
<![CDATA[
VITIS_LOOP_1681_5.split:2 %call_ln0 = call void @MatMul_QK_tiled.20_Pipeline_VITIS_LOOP_1682_6, i8 %tile_Q_V_0, i8 %Q_1_2

]]></Node>
<StgValue><ssdm name="call_ln0"/></StgValue>
</operation>

<operation id="28" st_id="4" stage="1" lat="1">
<core>NULL</core>
<MemPortIdVec></MemPortIdVec>
<condition id="-1">
<or_exp><and_exp><literal name="icmp_ln1678" val="0"/>
</and_exp></or_exp>
</condition>

<Node id="28" bw="0" op_0_bw="5" op_1_bw="5" op_2_bw="0" op_3_bw="0">
<![CDATA[
VITIS_LOOP_1681_5.split:6 %store_ln1678 = store i5 %m_15, i5 %m

]]></Node>
<StgValue><ssdm name="store_ln1678"/></StgValue>
</operation>

<operation id="29" st_id="4" stage="1" lat="1">
<core>NULL</core>
<MemPortIdVec></MemPortIdVec>
<condition id="-1">
<or_exp><and_exp><literal name="icmp_ln1678" val="1"/>
</and_exp></or_exp>
</condition>

<Node id="31" bw="0">
<![CDATA[
for.end218:0 %ret_ln1761 = ret

]]></Node>
<StgValue><ssdm name="ret_ln1761"/></StgValue>
</operation>
</state>

<state id="5" st_id="5">

<operation id="30" st_id="5" stage="1" lat="2">
<core></core>
<MemPortIdVec></MemPortIdVec>
<condition id="-1">
<or_exp><and_exp></and_exp></or_exp>
</condition>

<Node id="24" bw="0" op_0_bw="0" op_1_bw="8" op_2_bw="8" op_3_bw="0">
<![CDATA[
VITIS_LOOP_1681_5.split:2 %call_ln0 = call void @MatMul_QK_tiled.20_Pipeline_VITIS_LOOP_1682_6, i8 %tile_Q_V_0, i8 %Q_1_2

]]></Node>
<StgValue><ssdm name="call_ln0"/></StgValue>
</operation>
</state>

<state id="6" st_id="6">

<operation id="31" st_id="6" stage="1" lat="1">
<core>NULL</core>
<MemPortIdVec></MemPortIdVec>
<condition id="-1">
<or_exp><and_exp></and_exp></or_exp>
</condition>

<Node id="25" bw="32" op_0_bw="32" op_1_bw="0" op_2_bw="0">
<![CDATA[
VITIS_LOOP_1681_5.split:3 %empty_295 = wait i32 @_ssdm_op_Wait

]]></Node>
<StgValue><ssdm name="empty_295"/></StgValue>
</operation>
</state>

<state id="7" st_id="7">

<operation id="32" st_id="7" stage="1" lat="1">
<core>NULL</core>
<MemPortIdVec></MemPortIdVec>
<condition id="-1">
<or_exp><and_exp></and_exp></or_exp>
</condition>

<Node id="26" bw="32" op_0_bw="32" op_1_bw="0">
<![CDATA[
VITIS_LOOP_1681_5.split:4 %empty_296 = wait i32 @_ssdm_op_Wait

]]></Node>
<StgValue><ssdm name="empty_296"/></StgValue>
</operation>

<operation id="33" st_id="7" stage="2" lat="2">
<core></core>
<MemPortIdVec></MemPortIdVec>
<condition id="-1">
<or_exp><and_exp></and_exp></or_exp>
</condition>

<Node id="27" bw="0" op_0_bw="0" op_1_bw="8" op_2_bw="8" op_3_bw="8" op_4_bw="0" op_5_bw="0" op_6_bw="0" op_7_bw="0">
<![CDATA[
VITIS_LOOP_1681_5.split:5 %call_ln0 = call void @MatMul_QK_tiled.20_Pipeline_VITIS_LOOP_1701_8, i8 %tile_Q_V_0, i8 %buff_K_V, i8 %A_2

]]></Node>
<StgValue><ssdm name="call_ln0"/></StgValue>
</operation>
</state>

<state id="8" st_id="8">

<operation id="34" st_id="8" stage="1" lat="1">
<core>NULL</core>
<MemPortIdVec></MemPortIdVec>
<condition id="-1">
<or_exp><and_exp></and_exp></or_exp>
</condition>

<Node id="22" bw="0" op_0_bw="0" op_1_bw="0">
<![CDATA[
VITIS_LOOP_1681_5.split:0 %specloopname_ln1678 = specloopname void @_ssdm_op_SpecLoopName, void @empty_39

]]></Node>
<StgValue><ssdm name="specloopname_ln1678"/></StgValue>
</operation>

<operation id="35" st_id="8" stage="1" lat="2">
<core></core>
<MemPortIdVec></MemPortIdVec>
<condition id="-1">
<or_exp><and_exp></and_exp></or_exp>
</condition>

<Node id="27" bw="0" op_0_bw="0" op_1_bw="8" op_2_bw="8" op_3_bw="8" op_4_bw="0" op_5_bw="0" op_6_bw="0" op_7_bw="0">
<![CDATA[
VITIS_LOOP_1681_5.split:5 %call_ln0 = call void @MatMul_QK_tiled.20_Pipeline_VITIS_LOOP_1701_8, i8 %tile_Q_V_0, i8 %buff_K_V, i8 %A_2

]]></Node>
<StgValue><ssdm name="call_ln0"/></StgValue>
</operation>

<operation id="36" st_id="8" stage="1" lat="1">
<core>NULL</core>
<MemPortIdVec></MemPortIdVec>
<condition id="-1">
<or_exp><and_exp></and_exp></or_exp>
</condition>

<Node id="29" bw="0" op_0_bw="0">
<![CDATA[
VITIS_LOOP_1681_5.split:7 %br_ln1678 = br void %VITIS_LOOP_1681_5

]]></Node>
<StgValue><ssdm name="br_ln1678"/></StgValue>
</operation>
</state>
</state_list>


<ports>
<port id="46" name="Q_1_2" dir="0" iftype="3">
<core>NULL</core><StgValue><ssdm name="Q_1_2"/></StgValue>
</port>
<port id="47" name="K_1_2" dir="0" iftype="3">
<core>NULL</core><StgValue><ssdm name="K_1_2"/></StgValue>
</port>
<port id="48" name="A_2" dir="1" iftype="3">
<core>NULL</core><StgValue><ssdm name="A_2"/></StgValue>
</port>
</ports>


<dataflows>
<dataflow id="50" from="StgValue_49" to="m" fromId="49" toId="9">
</dataflow>
<dataflow id="52" from="StgValue_51" to="buff_K_V" fromId="51" toId="10">
</dataflow>
<dataflow id="53" from="StgValue_51" to="tile_Q_V_0" fromId="51" toId="11">
</dataflow>
<dataflow id="55" from="_ssdm_op_Wait" to="empty" fromId="54" toId="12">
</dataflow>
<dataflow id="57" from="MatMul_QK_tiled.20_Pipeline_VITIS_LOOP_1656_1_VITIS_LOOP_1657_2" to="call_ln0" fromId="56" toId="13">
</dataflow>
<dataflow id="58" from="buff_K_V" to="call_ln0" fromId="10" toId="13">
</dataflow>
<dataflow id="59" from="K_1_2" to="call_ln0" fromId="47" toId="13">
</dataflow>
<dataflow id="61" from="StgValue_60" to="store_ln1678" fromId="60" toId="14">
</dataflow>
<dataflow id="62" from="m" to="store_ln1678" fromId="9" toId="14">
</dataflow>
<dataflow id="63" from="MatMul_QK_tiled.20_Pipeline_VITIS_LOOP_1656_1_VITIS_LOOP_1657_2" to="call_ln0" fromId="56" toId="15">
</dataflow>
<dataflow id="64" from="buff_K_V" to="call_ln0" fromId="10" toId="15">
</dataflow>
<dataflow id="65" from="K_1_2" to="call_ln0" fromId="47" toId="15">
</dataflow>
<dataflow id="67" from="_ssdm_op_SpecInterface" to="specinterface_ln0" fromId="66" toId="16">
</dataflow>
<dataflow id="68" from="Q_1_2" to="specinterface_ln0" fromId="46" toId="16">
</dataflow>
<dataflow id="70" from="empty_0" to="specinterface_ln0" fromId="69" toId="16">
</dataflow>
<dataflow id="72" from="StgValue_71" to="specinterface_ln0" fromId="71" toId="16">
</dataflow>
<dataflow id="73" from="StgValue_71" to="specinterface_ln0" fromId="71" toId="16">
</dataflow>
<dataflow id="75" from="empty_26" to="specinterface_ln0" fromId="74" toId="16">
</dataflow>
<dataflow id="76" from="StgValue_71" to="specinterface_ln0" fromId="71" toId="16">
</dataflow>
<dataflow id="77" from="StgValue_71" to="specinterface_ln0" fromId="71" toId="16">
</dataflow>
<dataflow id="78" from="empty_26" to="specinterface_ln0" fromId="74" toId="16">
</dataflow>
<dataflow id="79" from="empty_26" to="specinterface_ln0" fromId="74" toId="16">
</dataflow>
<dataflow id="80" from="empty_26" to="specinterface_ln0" fromId="74" toId="16">
</dataflow>
<dataflow id="81" from="StgValue_71" to="specinterface_ln0" fromId="71" toId="16">
</dataflow>
<dataflow id="82" from="StgValue_71" to="specinterface_ln0" fromId="71" toId="16">
</dataflow>
<dataflow id="83" from="StgValue_71" to="specinterface_ln0" fromId="71" toId="16">
</dataflow>
<dataflow id="84" from="StgValue_71" to="specinterface_ln0" fromId="71" toId="16">
</dataflow>
<dataflow id="85" from="empty_26" to="specinterface_ln0" fromId="74" toId="16">
</dataflow>
<dataflow id="86" from="empty_26" to="specinterface_ln0" fromId="74" toId="16">
</dataflow>
<dataflow id="88" from="StgValue_87" to="specinterface_ln0" fromId="87" toId="16">
</dataflow>
<dataflow id="89" from="StgValue_71" to="specinterface_ln0" fromId="71" toId="16">
</dataflow>
<dataflow id="90" from="_ssdm_op_SpecInterface" to="specinterface_ln0" fromId="66" toId="17">
</dataflow>
<dataflow id="91" from="K_1_2" to="specinterface_ln0" fromId="47" toId="17">
</dataflow>
<dataflow id="92" from="empty_0" to="specinterface_ln0" fromId="69" toId="17">
</dataflow>
<dataflow id="93" from="StgValue_71" to="specinterface_ln0" fromId="71" toId="17">
</dataflow>
<dataflow id="94" from="StgValue_71" to="specinterface_ln0" fromId="71" toId="17">
</dataflow>
<dataflow id="95" from="empty_26" to="specinterface_ln0" fromId="74" toId="17">
</dataflow>
<dataflow id="96" from="StgValue_71" to="specinterface_ln0" fromId="71" toId="17">
</dataflow>
<dataflow id="97" from="StgValue_71" to="specinterface_ln0" fromId="71" toId="17">
</dataflow>
<dataflow id="98" from="empty_26" to="specinterface_ln0" fromId="74" toId="17">
</dataflow>
<dataflow id="99" from="empty_26" to="specinterface_ln0" fromId="74" toId="17">
</dataflow>
<dataflow id="100" from="empty_26" to="specinterface_ln0" fromId="74" toId="17">
</dataflow>
<dataflow id="101" from="StgValue_71" to="specinterface_ln0" fromId="71" toId="17">
</dataflow>
<dataflow id="102" from="StgValue_71" to="specinterface_ln0" fromId="71" toId="17">
</dataflow>
<dataflow id="103" from="StgValue_71" to="specinterface_ln0" fromId="71" toId="17">
</dataflow>
<dataflow id="104" from="StgValue_71" to="specinterface_ln0" fromId="71" toId="17">
</dataflow>
<dataflow id="105" from="empty_26" to="specinterface_ln0" fromId="74" toId="17">
</dataflow>
<dataflow id="106" from="empty_26" to="specinterface_ln0" fromId="74" toId="17">
</dataflow>
<dataflow id="107" from="StgValue_87" to="specinterface_ln0" fromId="87" toId="17">
</dataflow>
<dataflow id="108" from="StgValue_71" to="specinterface_ln0" fromId="71" toId="17">
</dataflow>
<dataflow id="109" from="_ssdm_op_SpecInterface" to="specinterface_ln0" fromId="66" toId="18">
</dataflow>
<dataflow id="110" from="A_2" to="specinterface_ln0" fromId="48" toId="18">
</dataflow>
<dataflow id="111" from="empty_0" to="specinterface_ln0" fromId="69" toId="18">
</dataflow>
<dataflow id="112" from="StgValue_71" to="specinterface_ln0" fromId="71" toId="18">
</dataflow>
<dataflow id="113" from="StgValue_71" to="specinterface_ln0" fromId="71" toId="18">
</dataflow>
<dataflow id="114" from="empty_26" to="specinterface_ln0" fromId="74" toId="18">
</dataflow>
<dataflow id="115" from="StgValue_71" to="specinterface_ln0" fromId="71" toId="18">
</dataflow>
<dataflow id="116" from="StgValue_71" to="specinterface_ln0" fromId="71" toId="18">
</dataflow>
<dataflow id="117" from="empty_26" to="specinterface_ln0" fromId="74" toId="18">
</dataflow>
<dataflow id="118" from="empty_26" to="specinterface_ln0" fromId="74" toId="18">
</dataflow>
<dataflow id="119" from="empty_26" to="specinterface_ln0" fromId="74" toId="18">
</dataflow>
<dataflow id="120" from="StgValue_71" to="specinterface_ln0" fromId="71" toId="18">
</dataflow>
<dataflow id="121" from="StgValue_71" to="specinterface_ln0" fromId="71" toId="18">
</dataflow>
<dataflow id="122" from="StgValue_71" to="specinterface_ln0" fromId="71" toId="18">
</dataflow>
<dataflow id="123" from="StgValue_71" to="specinterface_ln0" fromId="71" toId="18">
</dataflow>
<dataflow id="124" from="empty_26" to="specinterface_ln0" fromId="74" toId="18">
</dataflow>
<dataflow id="125" from="empty_26" to="specinterface_ln0" fromId="74" toId="18">
</dataflow>
<dataflow id="126" from="StgValue_87" to="specinterface_ln0" fromId="87" toId="18">
</dataflow>
<dataflow id="127" from="StgValue_71" to="specinterface_ln0" fromId="71" toId="18">
</dataflow>
<dataflow id="128" from="_ssdm_op_Wait" to="empty_292" fromId="54" toId="19">
</dataflow>
<dataflow id="129" from="m" to="m_14" fromId="9" toId="21">
</dataflow>
<dataflow id="130" from="m_14" to="icmp_ln1678" fromId="21" toId="22">
</dataflow>
<dataflow id="132" from="StgValue_131" to="icmp_ln1678" fromId="131" toId="22">
</dataflow>
<dataflow id="134" from="_ssdm_op_SpecLoopTripCount" to="empty_293" fromId="133" toId="23">
</dataflow>
<dataflow id="136" from="StgValue_135" to="empty_293" fromId="135" toId="23">
</dataflow>
<dataflow id="137" from="StgValue_135" to="empty_293" fromId="135" toId="23">
</dataflow>
<dataflow id="138" from="StgValue_135" to="empty_293" fromId="135" toId="23">
</dataflow>
<dataflow id="139" from="m_14" to="m_15" fromId="21" toId="24">
</dataflow>
<dataflow id="141" from="StgValue_140" to="m_15" fromId="140" toId="24">
</dataflow>
<dataflow id="142" from="icmp_ln1678" to="br_ln1678" fromId="22" toId="25">
</dataflow>
<dataflow id="143" from="_ssdm_op_Wait" to="empty_294" fromId="54" toId="26">
</dataflow>
<dataflow id="145" from="MatMul_QK_tiled.20_Pipeline_VITIS_LOOP_1682_6" to="call_ln0" fromId="144" toId="27">
</dataflow>
<dataflow id="146" from="tile_Q_V_0" to="call_ln0" fromId="11" toId="27">
</dataflow>
<dataflow id="147" from="Q_1_2" to="call_ln0" fromId="46" toId="27">
</dataflow>
<dataflow id="148" from="m_15" to="store_ln1678" fromId="24" toId="28">
</dataflow>
<dataflow id="149" from="m" to="store_ln1678" fromId="9" toId="28">
</dataflow>
<dataflow id="150" from="MatMul_QK_tiled.20_Pipeline_VITIS_LOOP_1682_6" to="call_ln0" fromId="144" toId="30">
</dataflow>
<dataflow id="151" from="tile_Q_V_0" to="call_ln0" fromId="11" toId="30">
</dataflow>
<dataflow id="152" from="Q_1_2" to="call_ln0" fromId="46" toId="30">
</dataflow>
<dataflow id="153" from="_ssdm_op_Wait" to="empty_295" fromId="54" toId="31">
</dataflow>
<dataflow id="154" from="_ssdm_op_Wait" to="empty_296" fromId="54" toId="32">
</dataflow>
<dataflow id="156" from="MatMul_QK_tiled.20_Pipeline_VITIS_LOOP_1701_8" to="call_ln0" fromId="155" toId="33">
</dataflow>
<dataflow id="157" from="tile_Q_V_0" to="call_ln0" fromId="11" toId="33">
</dataflow>
<dataflow id="158" from="buff_K_V" to="call_ln0" fromId="10" toId="33">
</dataflow>
<dataflow id="159" from="A_2" to="call_ln0" fromId="48" toId="33">
</dataflow>
<dataflow id="161" from="_ssdm_op_SpecLoopName" to="specloopname_ln1678" fromId="160" toId="34">
</dataflow>
<dataflow id="163" from="empty_39" to="specloopname_ln1678" fromId="162" toId="34">
</dataflow>
<dataflow id="164" from="MatMul_QK_tiled.20_Pipeline_VITIS_LOOP_1701_8" to="call_ln0" fromId="155" toId="35">
</dataflow>
<dataflow id="165" from="tile_Q_V_0" to="call_ln0" fromId="11" toId="35">
</dataflow>
<dataflow id="166" from="buff_K_V" to="call_ln0" fromId="10" toId="35">
</dataflow>
<dataflow id="167" from="A_2" to="call_ln0" fromId="48" toId="35">
</dataflow>
<dataflow id="168" from="icmp_ln1678" to="StgValue_4" fromId="22" toId="4">
</dataflow>
</dataflows>


</stg>
